python/__init__.py
python/client.py
discardapi_demo-0.1.0.dist-info/LICENSE
discardapi_demo-0.1.0.dist-info/METADATA
discardapi_demo-0.1.0.dist-info/WHEEL
discardapi_demo-0.1.0.dist-info/top_level.txt
discardapi_demo-0.1.0.dist-info/RECORD
