Metadata-Version: 2.1
Name: discardapi-demo
Version: 0.1.0
Summary: Python demo client for Discard API
Home-page: https://github.com/GlobalTechInfo/discardapi
Author: Qasim Ali
Author-email: discardapi@gmail.com
Requires-Python: >=3.7
License-File: LICENSE
Requires-Dist: requests
